{
	"c000_01": "c000_01_주인공",
	"c001_00": "c001_00_무명의_차일드",
	"c001_01": "c001_01_모나",
	"c001_02": "c001_02_모나",
	"c001_11": "c001_11",
	"c001_12": "c001_12",
	"c002_00": "c002_00_미성숙한_리자",
	"c002_01": "c002_01_리자",
	"c002_02": "c002_02_리자",
	"c003_00": "c003_00_무명의_차일드",
	"c003_01": "c003_01_다비",
	"c003_02": "c003_02_서큐버스_다비",
	"c004_00": "c004_00_미성숙한_처용",
	"c004_01": "c004_01_이웃의_처용",
	"c004_02": "c004_02_친절한_처용",
	"c005_00": "c005_00_미성숙한_마르스",
	"c005_01": "c005_01_질주하는_마르스",
	"c005_02": "c005_02_폭주하는_마르스",
	"c006_00": "c006_00_미성숙한_유노",
	"c006_01": "c006_01_유혹의_유노",
	"c006_02": "c006_02_순백의_유노",
	"c007_00": "c007_00_미성숙한_포이닉스",
	"c007_01": "c007_01_뜨거운_포이닉스",
	"c007_02": "c007_02_열화의_포이닉스",
	"c008_00": "c008_00_미성숙한_프리가",
	"c008_01": "c008_01_검사_프리가",
	"c008_02": "c008_02_검황_프리가",
	"c009_00": "c009_00_미성숙한_헥토르",
	"c009_01": "c009_01_병사_헥토르",
	"c009_02": "c009_02_해결사_헥토르",
	"c010_00": "c010_00_미성숙한_드미테르",
	"c010_01": "c010_01_허세의_드미테르",
	"c010_02": "c010_02_허영의_드미테르",
	"c010_03": "c010_03_무명의_차일드",
	"c011_00": "c011_00_미성숙한_데이노",
	"c011_01": "c011_01_봉사하는_데이노",
	"c011_02": "c011_02_헌납의_데이노",
	"c012_00": "c012_00_미성숙한_아가멤논",
	"c012_01": "c012_01_결투의_아가멤논",
	"c012_02": "c012_02_최후의_아가멤논",
	"c013_00": "c013_00_미성숙한_아르테미스",
	"c013_01": "c013_01_꿈의_아르테미스",
	"c013_02": "c013_02_신비의_아르테미스",
	"c014_00": "c014_00_미성숙한_아스트레아",
	"c014_01": "c014_01_별의_아스트레아",
	"c014_02": "c014_02_성단의_아스트레아",
	"c015_00": "c015_00_미성숙한_헬레나",
	"c015_01": "c015_01_시기의_헬레나",
	"c015_02": "c015_02_질투의_헬레나",
	"c016_00": "c016_00_미성숙한_리베르타스",
	"c016_01": "c016_01_전진_리베르타스",
	"c016_02": "c016_02_투쟁_리베르타스",
	"c017_00": "c017_00_미성숙한_왕군이",
	"c017_01": "c017_01_집지키는_왕군이",
	"c017_02": "c017_02_디펜스_왕군이",
	"c018_00": "c018_00_미성숙한_코라",
	"c018_01": "c018_01_꼬마_코라",
	"c018_02": "c018_02_미숙의_코라",
	"c019_00": "c019_00_미성숙한_에리스",
	"c019_01": "c019_01_거친_에리스",
	"c019_02": "c019_02_분노의_에리스",
	"c020_00": "c020_00_미성숙한_포르투나",
	"c020_01": "c020_01_위험한_포르투나",
	"c020_02": "c020_02_승부사_포르투나",
	"c021_00": "c021_00_미성숙한_오르페우스",
	"c021_01": "c021_01_잠든_오르페우스",
	"c021_02": "c021_02_후회의_오르페우스",
	"c022_00": "c022_00_미성숙한_마야우엘",
	"c022_01": "c022_01_나태의_마야우엘",
	"c022_02": "c022_02_한심의_마야우엘",
	"c023_00": "c023_00_무명의_차일드",
	"c023_01": "c023_01_카미뉴",
	"c023_02": "c023_02_군주_카미뉴",
	"c024_00": "c024_00_이웃집_루퍼스",
	"c024_01": "c024_01_루퍼스",
	"c024_02": "c024_02_대공_루퍼스",
	"c025_01": "c025_01_로키",
	"c025_02": "c025_02_공자_로키",
	"c026_00": "c026_00_미성숙한_오로라",
	"c026_01": "c026_01_기쁜_오로라",
	"c026_02": "c026_02_광희의_오로라",
	"c027_00": "c027_00_미성숙한_킨티아",
	"c027_01": "c027_01_자각한_킨티아",
	"c027_02": "c027_02_진정한_킨티아",
	"c028_00": "c028_00_미성숙한_레다",
	"c028_01": "c028_01_성공한_레다",
	"c028_02": "c028_02_찬란한_레다",
	"c029_00": "c029_00_미성숙한_셀레네",
	"c029_01": "c029_01_밤의_셀레네",
	"c029_02": "c029_02_달의_셀레네",
	"c030_00": "c030_00_미성숙한_소녀탐정",
	"c030_01": "c030_01_떠돌이_소녀탐정",
	"c030_02": "c030_02_통속계_소녀탐정",
	"c031_00": "c031_00_미성숙한_프레이야",
	"c031_01": "c031_01_순진한_프레이야",
	"c031_02": "c031_02_순수한_프레이야",
	"c032_00": "c032_00_미성숙한_알렉토",
	"c032_01": "c032_01_분주한_알렉토",
	"c032_02": "c032_02_쉬지않는_알렉토",
	"c033_00": "c033_00_미성숙한_다이아나",
	"c033_01": "c033_01_조용한_다이아나",
	"c033_02": "c033_02_은둔하는_다이아나",
	"c034_00": "c034_00_미성숙한_므네모시네",
	"c034_01": "c034_01_게으른_므네모시네",
	"c034_02": "c034_02_도도한_므네모시네",
	"c035_00": "c035_00_미성숙한_페르세포네",
	"c035_01": "c035_01_새벽녘_페르세포네",
	"c035_02": "c035_02_속박의_페르세포네",
	"c036_00": "c036_00_미성숙한_에르메스",
	"c036_01": "c036_01_낭비한_에르메스",
	"c036_02": "c036_02_지름의_에르메스",
	"c037_00": "c037_00_무명의_차일드",
	"c037_01": "c037_01_유다",
	"c037_02": "c037_02_암왕_유다",
	"c038_00": "c038_00_미성숙한_칼립소",
	"c038_01": "c038_01_짓궂은_칼립소",
	"c038_02": "c038_02_유혹하는_칼립소",
	"c039_00": "c039_00_미성숙한_베누스",
	"c039_01": "c039_01_왜소한_베누스",
	"c039_02": "c039_02_절제의_베누스",
	"c040_00": "c040_00_미성숙한_샤마시",
	"c040_01": "c040_01_질서의_샤마시",
	"c040_02": "c040_02_준법의_샤마시",
	"c041_00": "c041_00_미성숙한_티아마트",
	"c041_01": "c041_01_밤의_티아마트",
	"c041_02": "c041_02_심연의_티아마트",
	"c042_00": "c042_00_미성숙한_판도라",
	"c042_01": "c042_01_철저한_판도라",
	"c042_02": "c042_02_절삭된_판도라",
	"c043_00": "c043_00_미성숙한_헤라",
	"c043_01": "c043_01_긍지의_헤라",
	"c043_02": "c043_02_오만의_헤라",
	"c044_00": "c044_00_미성숙한_판테온",
	"c044_01": "c044_01_겉도는_판테온",
	"c044_02": "c044_02_방랑자_판테온",
	"c045_00": "c045_00_미성숙한_아리아",
	"c045_01": "c045_01_노래하는_아리아",
	"c045_02": "c045_02_환희하는_아리아",
	"c046_00": "c046_00_미성숙한_비루다",
	"c046_01": "c046_01_퇴마사_비루다",
	"c046_02": "c046_02_증장천_비루다",
	"c047_00": "c047_00_미성숙한_헤스티아",
	"c047_01": "c047_01_흑염의_헤스티아",
	"c047_02": "c047_02_백염의_헤스티아",
	"c048_00": "c048_00_미성숙한_네반",
	"c048_01": "c048_01_연모하는_네반",
	"c048_02": "c048_02_애증의_네반",
	"c049_00": "c049_00_미성숙한_마아트",
	"c049_01": "c049_01_미혹된_마아트",
	"c049_02": "c049_02_맹목적인_마아트",
	"c050_00": "c050_00_미성숙한_오드",
	"c050_01": "c050_01_오드",
	"c050_02": "c050_02_폭군_오드",
	"c051_00": "c051_00_미성숙한_프레이",
	"c051_01": "c051_01_프레이",
	"c051_02": "c051_02_악동_프레이",
	"c052_00": "c052_00_미성숙한_마후라가",
	"c052_01": "c052_01_교언의_마후라가",
	"c052_02": "c052_02_기만의_마후라가",
	"c053_00": "c053_00_미성숙한_메티스",
	"c053_01": "c053_01_망설이는_메티스",
	"c053_02": "c053_02_미래의_메티스",
	"c054_00": "c054_00_미성숙한_레전드",
	"c054_01": "c054_01_수호의_레전드",
	"c054_02": "c054_02_전설의_레전드",
	"c055_00": "c055_00_미성숙한_아테나",
	"c055_01": "c055_01_미약한_아테나",
	"c055_02": "c055_02_무적의_아테나",
	"c056_00": "c056_00_미성숙한_잔다르크",
	"c056_01": "c056_01_희생하는_잔다르크",
	"c056_02": "c056_02_헌신하는_잔다르크",
	"c057_00": "c057_00_미성숙한_란페이",
	"c057_01": "c057_01_란페이",
	"c057_02": "c057_02_흑성_란페이",
	"c058_00": "c058_00_미성숙한_니르리티",
	"c058_01": "c058_01_퇴마사_니르리티",
	"c058_02": "c058_02_나찰천_니르리티",
	"c059_00": "c059_00_미성숙한_인드라",
	"c059_01": "c059_01_퇴마사_인드라",
	"c059_02": "c059_02_제석천_인드라",
	"c060_00": "c060_00_미성숙한_티시포네",
	"c060_01": "c060_01_역습_티시포네",
	"c060_02": "c060_02_복수자_티시포네",
	"c061_00": "c061_00_미성숙한_세이렌",
	"c061_01": "c061_01_무명의_세이렌",
	"c061_02": "c061_02_심야의_세이렌",
	"c062_00": "c062_00_미성숙한_에우로페",
	"c062_01": "c062_01_향기의_에우로페",
	"c062_02": "c062_02_매혹의_에우로페",
	"c063_00": "c063_00_미성숙한_프리지아",
	"c063_01": "c063_01_내심의_프리지아",
	"c063_02": "c063_02_억측의_프리지아",
	"c064_00": "c064_00_미성숙한_메두사",
	"c064_01": "c064_01_차가운_메두사",
	"c064_02": "c064_02_냉혈의_메두사",
	"c065_00": "c065_00_미성숙한_에라토",
	"c065_01": "c065_01_피어난_에라토",
	"c065_02": "c065_02_백화요란_에라토",
	"c066_00": "c066_00_미성숙한_아텐",
	"c066_01": "c066_01_독선적인_아텐",
	"c066_02": "c066_02_책략가_아텐",
	"c067_00": "c067_00_미성숙한_타나토스",
	"c067_01": "c067_01_미지의_타나토스",
	"c067_02": "c067_02_초연한_타나토스",
	"c068_00": "c068_00_미성숙한_암브로시아",
	"c068_01": "c068_01_도전자_암브로시아",
	"c068_02": "c068_02_미식의_암브로시아",
	"c069_00": "c069_00_미성숙한_프타",
	"c069_01": "c069_01_핸디맨_프타",
	"c069_02": "c069_02_조율의_프타",
	"c070_00": "c070_00_미성숙한_유이",
	"c070_01": "c070_01_미래의_유이",
	"c070_02": "c070_02_모두의_유이",
	"c071_00": "c071_00_미성숙한_케레스",
	"c071_01": "c071_01_포기한_케레스",
	"c071_02": "c071_02_절망한_케레스",
	"c072_00": "c072_00_미성숙한_펜릴",
	"c072_01": "c072_01_탐색하는_펜릴",
	"c072_02": "c072_02_그림자_펜릴",
	"c073_00": "c073_00_미성숙한_클리메네",
	"c073_01": "c073_01_자조하는_클리메네",
	"c073_02": "c073_02_희망의_클리메네",
	"c074_00": "c074_00_미성숙한_키리누스",
	"c074_01": "c074_01_힘내는_키리누스",
	"c074_02": "c074_02_열렬한_키리누스",
	"c075_00": "c075_00_미성숙한_탄하",
	"c075_01": "c075_01_농향의_탄하",
	"c075_02": "c075_02_향락의_탄하",
	"c076_00": "c076_00_미성숙한_아이아스",
	"c076_01": "c076_01_면역의_아이아스",
	"c076_02": "c076_02_백색_아이아스",
	"c077_00": "c077_00_미성숙한_오이노네",
	"c077_01": "c077_01_기다리는_오이노네",
	"c077_02": "c077_02_배반의_오이노네",
	"c078_00": "c078_00_미성숙한_차일드",
	"c078_01": "c078_01_무장_니오베",
	"c078_02": "c078_02_투희_니오베",
	"c079_00": "c079_00_미성숙한_키르케",
	"c079_01": "c079_01_설렘의_키르케",
	"c079_02": "c079_02_혼탁한_키르케",
	"c080_00": "c080_00_미성숙한_아이기나",
	"c080_01": "c080_01_미소짓는_아이기나",
	"c080_02": "c080_02_즐거운_아이기나",
	"c081_00": "c081_00_미성숙한_테미스",
	"c081_01": "c081_01_끊어진_테미스",
	"c081_02": "c081_02_떠도는_테미스",
	"c082_00": "c082_00_미성숙한_칼카스",
	"c082_01": "c082_01_노련한_칼카스",
	"c082_02": "c082_02_선지안_칼카스",
	"c083_00": "c083_00_미성숙한_네이드",
	"c083_01": "c083_01_전장의_네이드",
	"c083_02": "c083_02_여단장_네이드",
	"c084_00": "c084_00_미성숙한_엘피쉬",
	"c084_01": "c084_01_작은_엘피쉬",
	"c084_02": "c084_02_장난스런_엘피쉬",
	"c085_00": "c085_00_미성숙한_파리스",
	"c085_01": "c085_01_독설가_파리스",
	"c085_02": "c085_02_심판_파리스",
	"c086_00": "c086_00_미성숙한_고가",
	"c086_01": "c086_01_조미의_고가",
	"c086_02": "c086_02_풍미의_고가",
	"c087_00": "c087_00_미성숙한_니누르타",
	"c087_01": "c087_01_순백의_니누르타",
	"c087_02": "c087_02_광휘의_니누르타",
	"c088_00": "c088_00_미성숙한_트로이",
	"c088_01": "c088_01_포화의_트로이",
	"c088_02": "c088_02_침략자_트로이",
	"c089_00": "c089_00_미성숙한_루나",
	"c089_01": "c089_01_침체된_루나",
	"c089_02": "c089_02_공허한_루나",
	"c090_00": "c090_00_미성숙한_불카누스",
	"c090_01": "c090_01_소생의_불카누스",
	"c090_02": "c090_02_부활의_불카누스",
	"c091_00": "c091_00_미성숙한_마이라",
	"c091_01": "c091_01_수호의_마이라",
	"c091_02": "c091_02_충성의_마이라",
	"c092_00": "c092_00_미성숙한_아르미드",
	"c092_01": "c092_01_일격의_아르미드",
	"c092_02": "c092_02_결벽의_아르미드",
	"c093_00": "c093_00_미성숙한_앙게로나",
	"c093_01": "c093_01_침묵의_앙게로나",
	"c093_02": "c093_02_정착의_앙게로나",
	"c094_00": "c094_00_미성숙한_미돈",
	"c094_01": "c094_01_충직한_미돈",
	"c094_02": "c094_02_반격의_미돈",
	"c095_00": "c095_00_미성숙한_베스타",
	"c095_01": "c095_01_열혈_베스타",
	"c095_02": "c095_02_멸화의_베스타",
	"c096_00": "c096_00_미성숙한_니레우스",
	"c096_01": "c096_01_희미한_니레우스",
	"c096_02": "c096_02_비탄의_니레우스",
	"c097_00": "c097_00_미성숙한_차일드",
	"c097_01": "c097_01_무명의_차일드",
	"c097_02": "c097_02_무명의_차일드",
	"c098_00": "c098_00_미성숙한_카라스",
	"c098_01": "c098_01_검은_카라스",
	"c098_02": "c098_02_효조_카라스",
	"c099_00": "c099_00_미성숙한_멜포메네",
	"c099_01": "c099_01_지루한_멜포메네",
	"c099_02": "c099_02_굉음_멜포메네",
	"c100_00": "c100_00_미성숙한_야만타카",
	"c100_01": "c100_01_분에의_야만타카",
	"c100_02": "c100_02_진에의_야만타카",
	"c101_00": "c101_00_미성숙한_시링크스",
	"c101_01": "c101_01_순수_시링크스",
	"c101_02": "c101_02_순결한_시링크스",
	"c102_00": "c102_00_미성숙한_차일드",
	"c102_01": "c102_01_무명의_차일드",
	"c102_02": "c102_02_무명의_차일드",
	"c103_00": "c103_00_미성숙한_아모스",
	"c103_01": "c103_01_독심의_아모스",
	"c103_02": "c103_02_예언가_아모스",
	"c104_00": "c104_00_미성숙한_게이렐",
	"c104_01": "c104_01_전진의_게이렐",
	"c104_02": "c104_02_선봉_게이렐",
	"c105_00": "c105_00_무명의_차일드",
	"c105_01": "c105_01_무명의_차일드",
	"c105_02": "c105_02_무명의_차일드",
	"c106_00": "c106_00_미성숙한_메데이아",
	"c106_01": "c106_01_마법사_메데이아",
	"c106_02": "c106_02_음모의_메데이아",
	"c107_00": "c107_00_미성숙한_아폴론",
	"c107_01": "c107_01_찬란한_아폴론",
	"c107_02": "c107_02_숭배받는_아폴론",
	"c108_00": "c108_00_무명의_차일드",
	"c108_01": "c108_01_무명의_차일드",
	"c108_02": "c108_02_무명의_차일드",
	"c109_00": "c109_00_미성숙한_아레투사",
	"c109_01": "c109_01_청음의_아레투사",
	"c109_02": "c109_02_만개한_아레투사",
	"c110_00": "c110_00_미성숙한_마르두크",
	"c110_01": "c110_01_집념의_마르두크",
	"c110_02": "c110_02_챌린저_마르두크",
	"c111_00": "c111_00_미성숙한_차일드",
	"c111_01": "c111_01_무명의_차일드",
	"c111_02": "c111_02_무명의_차일드",
	"c112_00": "c112_00_미성숙한_엘리어스",
	"c112_01": "c112_01_구도자_엘리어스",
	"c112_02": "c112_02_현자_엘리어스",
	"c113_00": "c113_00_미성숙한_쿠마에",
	"c113_01": "c113_01_반항의_쿠마에",
	"c113_02": "c113_02_저항의_쿠마에",
	"c114_00": "c114_00_미성숙한_차일드",
	"c114_01": "c114_01_무명의_차일드",
	"c114_02": "c114_02_무명의_차일드",
	"c115_00": "c115_00_미성숙한_소네트",
	"c115_01": "c115_01_슬픔의_소네트",
	"c115_02": "c115_02_화해의_소네트",
	"c116_00": "c116_00_미성숙한_플루토",
	"c116_01": "c116_01_예리한_플루토",
	"c116_02": "c116_02_프리마_플루토",
	"c117_00": "c117_00_미성숙한_야가",
	"c117_01": "c117_01_성실한_야가",
	"c117_02": "c117_02_독실한_야가",
	"c118_00": "c118_00_미성숙한_차일드",
	"c118_01": "c118_01_무명의_차일드",
	"c118_02": "c118_02_무명의_차일드",
	"c119_00": "c119_00_미성숙한_차일드",
	"c119_01": "c119_01_무명의_차일드",
	"c119_02": "c119_02_무명의_차일드",
	"c120_00": "c120_00_미성숙한_플로라",
	"c120_01": "c120_01_들판의_플로라",
	"c120_02": "c120_02_자유로운_플로라",
	"c121_00": "c121_00_미성숙한_뮤즈",
	"c121_01": "c121_01_밤의_뮤즈",
	"c121_02": "c121_02_굉음의_뮤즈",
	"c122_00": "c122_00_미성숙한_사마엘",
	"c122_01": "c122_01_지켜보는_사마엘",
	"c122_02": "c122_02_방관자_사마엘",
	"c123_00": "c123_00_미성숙한_바포메",
	"c123_01": "c123_01_창조된_바포메",
	"c123_02": "c123_02_환성의_바포메",
	"c124_00": "c124_00_미성숙한_이브",
	"c124_01": "c124_01_금단_이브",
	"c124_02": "c124_02_원죄_이브",
	"c125_00": "c125_00_미성숙한_아티스",
	"c125_01": "c125_01_지상의_아티스",
	"c125_02": "c125_02_희극_아티스",
	"c126_00": "c126_00_미성숙한_살마키스",
	"c126_01": "c126_01_순정_살마키스",
	"c126_02": "c126_02_당신의_살마키스",
	"c127_00": "c127_00_미성숙한_바스테트",
	"c127_01": "c127_01_사나운_바스테트",
	"c127_02": "c127_02_환야의_바스테트",
	"c128_00": "c128_00_미성숙한_갈라테아",
	"c128_01": "c128_01_파편의_갈라테아",
	"c128_02": "c128_02_이상의_갈라테아",
	"c129_00": "c129_00_미성숙한_니케",
	"c129_01": "c129_01_명예로운_니케",
	"c129_02": "c129_02_여황_니케",
	"c130_00": "c130_00_미성숙한_게니우스",
	"c130_01": "c130_01_명장_게니우스",
	"c130_02": "c130_02_마스터_게니우스",
	"c131_00": "c131_00_미성숙한_오시리스",
	"c131_01": "c131_01_돌아온_오시리스",
	"c131_02": "c131_02_사자_오시리스",
	"c132_00": "c132_00_미성숙한_미다스",
	"c132_01": "c132_01_여유의_미다스",
	"c132_02": "c132_02_탐미_미다스",
	"c133_00": "c133_00_미성숙한_티타니아",
	"c133_01": "c133_01_결전의_티타니아",
	"c133_02": "c133_02_대단원_티타니아",
	"c134_00": "c134_00_미성숙한_베네리스",
	"c134_01": "c134_01_격노_베네리스",
	"c134_02": "c134_02_매혹_베네리스",
	"c135_00": "c135_00_미성숙한_발키리",
	"c135_01": "c135_01_전사_발키리",
	"c135_02": "c135_02_야성의_발키리",
	"c136_00": "c136_00_미성숙한_네메시스",
	"c136_01": "c136_01_복수하는_네메시스",
	"c136_02": "c136_02_압도하는_네메시스",
	"c137_00": "c137_00_미성숙한_미트라",
	"c137_01": "c137_01_퇴색한_미트라",
	"c137_02": "c137_02_파계_미트라",
	"c138_00": "c138_00_미성숙한_차일드",
	"c138_01": "c138_01_무명의_차일드",
	"c138_02": "c138_02_무명의_차일드",
	"c139_00": "c139_00_미성숙한_포모나",
	"c139_01": "c139_01_화원의_포모나",
	"c139_02": "c139_02_숨은_포모나",
	"c140_00": "c140_00_미성숙한_노덴스",
	"c140_01": "c140_01_감시하는_노덴스",
	"c140_02": "c140_02_추격하는_노덴스",
	"c141_00": "c141_00_미성숙한_아모르",
	"c141_01": "c141_01_혼잣말_아모르",
	"c141_02": "c141_02_외사랑_아모르",
	"c142_00": "c142_00_미성숙한_히프노스",
	"c142_01": "c142_01_꿈꾸는_히프노스",
	"c142_02": "c142_02_몽상가_히프노스",
	"c143_00": "c143_00_미성숙한_차일드",
	"c143_01": "c143_01_무명의_차일드",
	"c143_02": "c143_02_무명의_차일드",
	"c144_00": "c144_00_미성숙한_메데아",
	"c144_01": "c144_01_검은밤_메데아",
	"c144_02": "c144_02_축제의_메데아",
	"c145_00": "c145_00_미성숙한_차일드",
	"c145_01": "c145_01_무명의_차일드",
	"c145_02": "c145_02_무명의_차일드",
	"c146_00": "c146_00_미성숙한_차일드",
	"c146_01": "c146_01_무명의_차일드",
	"c146_02": "c146_02_무명의_차일드",
	"c147_00": "c147_00_미성숙한_야차",
	"c147_01": "c147_01_퇴마사_야차",
	"c147_02": "c147_02_라크샤사_야차",
	"c148_00": "c148_00_미성숙한_이난나",
	"c148_01": "c148_01_어릿광대_이난나",
	"c148_02": "c148_02_폭군_이난나",
	"c149_00": "c149_00_미성숙한_루살카",
	"c149_01": "c149_01_망설이는_루살카",
	"c149_02": "c149_02_고백의_루살카",
	"c150_00": "c150_00_미성숙한_차일드",
	"c150_01": "c150_01_무명의_차일드",
	"c150_02": "c150_02_무명의_차일드",
	"c151_00": "c151_00_미성숙한_차일드",
	"c151_01": "c151_01_무명의_차일드",
	"c151_02": "c151_02_무명의_차일드",
	"c152_00": "c152_00_미성숙한_헤베",
	"c152_01": "c152_01_여름의_헤베",
	"c152_02": "c152_02_청춘의_헤베",
	"c153_00": "c153_00_미성숙한_에포나",
	"c153_01": "c153_01_모험가_에포나",
	"c153_02": "c153_02_먼곳의_에포나",
	"c154_00": "c154_00_미성숙한_바루나",
	"c154_01": "c154_01_엄격한_바루나",
	"c154_02": "c154_02_혹독한_바루나",
	"c155_00": "c155_00_미성숙한_에코",
	"c155_01": "c155_01_노래하는_에코",
	"c155_02": "c155_02_아이돌_에코",
	"c156_00": "c156_00_미성숙한_에르제베트",
	"c156_01": "c156_01_지배자_에르제베트",
	"c156_02": "c156_02_여제_에르제베트",
	"c157_00": "c157_00_미성숙한_아그니",
	"c157_01": "c157_01_퇴마사_아그니",
	"c157_02": "c157_02_화천_아그니",
	"c158_00": "c158_00_미성숙한_나이아스",
	"c158_01": "c158_01_수면의_나이아스",
	"c158_02": "c158_02_메르헨_나이아스",
	"c159_00": "c159_00_미성숙한_세멜레",
	"c159_01": "c159_01_세멜레",
	"c159_02": "c159_02_소악마_세멜레",
	"c160_00": "c160_00_미성숙한_사라",
	"c160_01": "c160_01_상냥한_사라",
	"c160_02": "c160_02_미소의_사라",
	"c161_00": "c161_00_미성숙한_유스티티아",
	"c161_01": "c161_01_심판의_유스티티아",
	"c161_02": "c161_02_처벌하는_유스티티아",
	"c162_01": "c162_01_무명의_차일드",
	"c162_02": "c162_02_무명의_차일드",
	"c163_00": "c163_00_미성숙한_샤리트",
	"c163_01": "c163_01_심해의_샤리트",
	"c163_02": "c163_02_흉수_샤리트",
	"c164_00": "c164_00_미성숙한_이슈타르",
	"c164_01": "c164_01_속박의_이슈타르",
	"c164_02": "c164_02_해방된_이슈타르",
	"c165_00": "c165_00_미성숙한_파르바티",
	"c165_01": "c165_01_숲속의_파르바티",
	"c165_02": "c165_02_첫사랑_파르바티",
	"c166_00": "c166_00_미성숙한_타와레트",
	"c166_01": "c166_01_자상한_타와레트",
	"c166_02": "c166_02_흑조_타와레트",
	"c167_00": "c167_00_미성숙한_상아",
	"c167_01": "c167_01_양지의_상아",
	"c167_02": "c167_02_현신_상아",
	"c168_00": "c168_00_미성숙한_탈리아",
	"c168_01": "c168_01_응원단_탈리아",
	"c168_02": "c168_02_환성_탈리아",
	"c169_00": "c169_00_미성숙한_에우로스",
	"c169_01": "c169_01_기쁜_에우로스",
	"c169_02": "c169_02_광휘의_에우로스",
	"c170_00": "c170_00_미성숙한_헤니르",
	"c170_01": "c170_01_헤니르",
	"c170_02": "c170_02_비소_헤니르",
	"c171_00": "c171_00_미성숙한_포이보스",
	"c171_01": "c171_01_나른한_포이보스",
	"c171_02": "c171_02_신예_포이보스",
	"c172_00": "c172_00_미성숙한_유나",
	"c172_01": "c172_01_빛나는_유나",
	"c172_02": "c172_02_찬란한_유나",
	"c173_00": "c173_00_미성숙한_디나시",
	"c173_01": "c173_01_작은_디나시",
	"c173_02": "c173_02_꼬마님_디나시",
	"c174_00": "c174_00_미성숙한_A.I",
	"c174_01": "c174_01_A.I",
	"c174_02": "c174_02_리미티드_A.I",
	"c175_00": "c175_00_미성숙한_레드크로스",
	"c175_01": "c175_01_파수꾼_레드크로스",
	"c175_02": "c175_02_수호자_레드크로스",
	"c176_00": "c176_00_미성숙한_에슈",
	"c176_01": "c176_01_바람잡이_에슈",
	"c176_02": "c176_02_딜러_에슈",
	"c177_00": "c177_00_미성숙한_프레타",
	"c177_01": "c177_01_움켜쥐는_프레타",
	"c177_02": "c177_02_탐식의_프레타",
	"c178_00": "c178_00_미성숙한_모르가나",
	"c178_01": "c178_01_신기루_모르가나",
	"c178_02": "c178_02_환상의_모르가나",
	"c179_00": "c179_00_미성숙한_이카루스",
	"c179_01": "c179_01_도약하는_이카루스",
	"c179_02": "c179_02_지평의_이카루스",
	"c180_00": "c180_00_미성숙한_맘몬",
	"c180_01": "c180_01_야망의_맘몬",
	"c180_02": "c180_02_탐욕의_맘몬",
	"c181_00": "c181_00_미성숙한_데브니",
	"c181_01": "c181_01_순수한_데브니",
	"c181_02": "c181_02_암전_데브니",
	"c182_00": "c182_00_미성숙한_차일드",
	"c182_01": "c182_01_무명의_차일드",
	"c182_02": "c182_02_각성_차일드",
	"c183_00": "c183_00_미성숙한_다나",
	"c183_01": "c183_01_설교하는_다나",
	"c183_02": "c183_02_전달자_다나",
	"c184_00": "c184_00_미성숙한_엘리시온",
	"c184_01": "c184_01_유랑아_엘리시온",
	"c184_02": "c184_02_낙원의_엘리시온",
	"c185_00": "c185_00_미성숙한_헤르모드",
	"c185_01": "c185_01_만용의_헤르모드",
	"c185_02": "c185_02_독재자_헤르모드",
	"c186_00": "c186_00_미성숙한_에레보스",
	"c186_01": "c186_01_통제하는_에레보스",
	"c186_02": "c186_02_지배자_에레보스",
	"c187_00": "c187_00_미성숙한_테티스",
	"c187_01": "c187_01_비탄의_테티스",
	"c187_02": "c187_02_애수_테티스",
	"c188_00": "c188_00_미성숙한_아탈란테",
	"c188_01": "c188_01_돌격_아탈란테",
	"c188_02": "c188_02_명조수_아탈란테",
	"c189_00": "c189_00_무명의_차일드",
	"c189_01": "c189_01_포박하는_크라토스",
	"c189_02": "c189_02_해방하는_크라토스",
	"c190_00": "c190_00_미성숙한_이시스",
	"c190_01": "c190_01_흉내내는_이시스",
	"c190_02": "c190_02_명배우_이시스",
	"c190_03": "c190_03",
	"c191_00": "c191_00_미성숙한_세크메트",
	"c191_01": "c191_01_파괴의_세크메트",
	"c191_02": "c191_02_격노한_세크메트",
	"c192_00": "c192_00_미성숙한_아라크네",
	"c192_01": "c192_01_싸우는_아라크네",
	"c192_02": "c192_02_격전의_아라크네",
	"c193_00": "c193_00_미성숙한_비루파",
	"c193_01": "c193_01_퇴마사_비루파",
	"c193_02": "c193_02_광목천_비루파",
	"c194_00": "c194_00_미성숙한_아슈토레스",
	"c194_01": "c194_01_백의_아슈토레스",
	"c194_02": "c194_02_순백_아슈토레스",
	"c195_00": "c195_00_미성숙한_키벨레",
	"c195_01": "c195_01_소공녀_키벨레",
	"c195_02": "c195_02_흑공녀_키벨레",
	"c196_00": "c196_00_미성숙한_이둔",
	"c196_01": "c196_01_화원의_이둔",
	"c196_02": "c196_02_매혹의_이둔",
	"c197_00": "c197_00_미성숙한_프리네",
	"c197_01": "c197_01_고고한_프리네",
	"c197_02": "c197_02_귀부인_프리네",
	"c198_00": "c198_00_미성숙한_젤로스",
	"c198_01": "c198_01_침묵의_젤로스",
	"c198_02": "c198_02_배반자_젤로스",
	"c199_00": "c199_00_미성숙한_아우로라",
	"c199_01": "c199_01_서쪽의_아우로라",
	"c199_02": "c199_02_아가페_아우로라",
	"c200_00": "c200_00_미성숙한_세스헤트",
	"c200_01": "c200_01_달리는_세스헤트",
	"c200_02": "c200_02_해결사_세스헤트",
	"c201_00": "c201_00_미성숙한_차일드",
	"c201_01": "c201_01_무명의_차일드",
	"c201_02": "c201_02_각성_차일드",
	"c202_00": "c202_00_미성숙한_빅트릭스",
	"c202_01": "c202_01_거울의_빅트릭스",
	"c202_02": "c202_02_인연의_빅트릭스",
	"c203_00": "c203_00_미성숙한_헬",
	"c203_01": "c203_01_물어뜯는_헬",
	"c203_02": "c203_02_조련사_헬",
	"c204_00": "c204_00_미성숙한_마이나데스",
	"c204_01": "c204_01_사냥꾼_마이나데스",
	"c204_02": "c204_02_침략자_마이나데스",
	"c205_00": "c205_00_미성숙한_멀린",
	"c205_01": "c205_01_이계의_멀린",
	"c205_02": "c205_02_방문자_멀린",
	"c206_00": "c206_00_미성숙한_녹스",
	"c206_01": "c206_01_반야_녹스",
	"c206_02": "c206_02_극야_녹스",
	"c207_00": "c207_00_미성숙한_파에톤",
	"c207_01": "c207_01_끓는_파에톤",
	"c207_02": "c207_02_작열_파에톤",
	"c208_00": "c208_00_미성숙한_파이로",
	"c208_01": "c208_01_뜨거운_파이로",
	"c208_02": "c208_02_열화의_파이로",
	"c209_00": "c209_00_미성숙한_헤카테",
	"c209_01": "c209_01_상상하는_헤카테",
	"c209_02": "c209_02_꿈꾸는_헤카테",
	"c210_00": "c210_00_미성숙한_타르타로스",
	"c210_01": "c210_01_심연의_타르타로스",
	"c210_02": "c210_02_제왕_타르타로스",
	"c211_00": "c211_00_미성숙한_시프",
	"c211_01": "c211_01_윤무곡_시프",
	"c211_02": "c211_02_찬가_시프",
	"c212_00": "c212_00_미성숙한_엠푸사",
	"c212_01": "c212_01_속삭이는_엠푸사",
	"c212_02": "c212_02_밤의신부_엠푸사",
	"c213_00": "c213_00_미성숙한_나가",
	"c213_01": "c213_01_여명_나가",
	"c213_02": "c213_02_칠성_나가",
	"c214_00": "c214_00_미성숙한_주피터",
	"c214_01": "c214_01_시험하는_주피터",
	"c214_02": "c214_02_재패의_주피터",
	"c215_00": "c215_00_미성숙한_수르트",
	"c215_01": "c215_01_극염_수르트",
	"c215_02": "c215_02_화도_수르트",
	"c216_00": "c216_00_미성숙한_워울프",
	"c216_01": "c216_01_달밤의_워울프",
	"c216_02": "c216_02_삼하인의_워울프",
	"c217_00": "c217_00_미성숙한_나우테스",
	"c217_01": "c217_01_꿰뚫는_나우테스",
	"c217_02": "c217_02_천리안_나우테스",
	"c218_00": "c218_00_미성숙한_알브",
	"c218_01": "c218_01_충만한_알브",
	"c218_02": "c218_02_행복의_알브",
	"c219_00": "c219_00_미성숙한_이미르",
	"c219_01": "c219_01_망각의_이미르",
	"c219_02": "c219_02_도려내는_이미르",
	"c220_00": "c220_00_미성숙한_아트로포스",
	"c220_01": "c220_01_질주의_아트로포스",
	"c220_02": "c220_02_진격의_아트로포스",
	"c221_00": "c221_00_미성숙한_야나",
	"c221_01": "c221_01_만월_야나",
	"c221_02": "c221_02_낙원_야나",
	"c222_00": "c222_00_미성숙한_엘도라도",
	"c222_01": "c222_01_황홀한_엘도라도",
	"c222_02": "c222_02_이상의_엘도라도",
	"c223_00": "c223_00_미성숙한_에아",
	"c223_01": "c223_01_표류하는_에아",
	"c223_02": "c223_02_방랑하는_에아",
	"c224_01": "c224_01_로키",
	"c225_00": "c225_00_미성숙한_루돌프",
	"c225_01": "c225_01_불청객_루돌프",
	"c225_02": "c225_02_밤도둑_루돌프",
	"c226_00": "c226_00_미성숙한_라그나르",
	"c226_01": "c226_01_노략꾼_라그나르",
	"c226_02": "c226_02_정복자_라그나르",
	"c227_00": "c227_00_미성숙한_마프데트",
	"c227_01": "c227_01_정의의_마프데트",
	"c227_02": "c227_02_독단의_마프데트",
	"c228_00": "c228_00_미성숙한_비비안",
	"c228_01": "c228_01_휘감는_비비안",
	"c228_02": "c228_02_감싸는_비비안",
	"c229_00": "c229_00_미성숙한_브라우니",
	"c229_01": "c229_01_소식통_브라우니",
	"c229_02": "c229_02_배달부_브라우니",
	"c230_00": "c230_00_미성숙한_스쿨드",
	"c230_01": "c230_01_저주의_스쿨드",
	"c230_02": "c230_02_멸절하는_스쿨드",
	"c231_00": "c231_00_미성숙한_레아실비아",
	"c231_01": "c231_01_찬미의_레아실비아",
	"c231_02": "c231_02_유혹의_레아실비아",
	"c232_00": "c232_00_미성숙한_다프네",
	"c232_01": "c232_01_환상_다프네",
	"c232_02": "c232_02_이상향_다프네",
	"c233_00": "c233_00_미성숙한_아르계스",
	"c233_01": "c233_01_전광_아르게스",
	"c233_02": "c233_02_백광_아르게스",
	"c234_00": "c234_00_미성숙한_헤라클레스",
	"c234_01": "c234_01_투지_헤라클레스",
	"c234_02": "c234_02_과업의_헤라클레스",
	"c235_00": "c235_00_미성숙한_다누",
	"c235_01": "c235_01_일촉즉발_다누",
	"c235_02": "c235_02_안티히어로_다누",
	"c236_00": "c236_00_미성숙한_스카하다",
	"c236_01": "c236_01_매지션_스카하다",
	"c236_02": "c236_02_감싸는_스카하다",
	"c237_00": "c237_00_미성숙한_티폰",
	"c237_01": "c237_01_밤의축제_티폰",
	"c237_02": "c237_02_삼하인_티폰",
	"c238_00": "c238_00_미성숙한_메브",
	"c238_01": "c238_01_하모니_메브",
	"c238_02": "c238_02_프리마_메브",
	"c239_00": "c239_00_미성숙한_디아누스",
	"c239_01": "c239_01_밤의_디아누스",
	"c239_02": "c239_02_백야_디아누스",
	"c240_00": "c240_00_미성숙한_야누스",
	"c240_01": "c240_01_한낮_야누스",
	"c240_02": "c240_02_흑해_야누스",
	"c241_00": "c241_00_미성숙한_오르쿠스",
	"c241_01": "c241_01_지하의_오르쿠스",
	"c241_02": "c241_02_매드닥터_오르쿠스",
	"c242_00": "c242_00_미성숙한_알릴",
	"c242_01": "c242_01_환술사_알릴",
	"c242_02": "c242_02_퍼레이드_알릴",
	"c243_00": "c243_00_미성숙한_보덴",
	"c243_01": "c243_01_혈전_보덴",
	"c243_02": "c243_02_광란_보덴",
	"c244_01": "c244_01_타이즈_춘리",
	"c244_02": "c244_02_드레스_춘리",
	"c245_01": "c245_01_베레모_캐미",
	"c245_02": "c245_02_제로_캐미",
	"c246_00": "c246_00_미성숙한_크람푸스",
	"c246_01": "c246_01_기만의_크람푸스",
	"c246_02": "c246_02_협잡꾼_크람푸스",
	"c247_00": "c247_00_미성숙한_미리나",
	"c247_01": "c247_01_여주인_미리나",
	"c247_02": "c247_02_여왕_미리나",
	"c248_00": "c248_00_미성숙한_디케",
	"c248_01": "c248_01_처형자_디케",
	"c248_02": "c248_02_재판관_디케",
	"c249_00": "c249_00_미성숙한_산타클로스",
	"c249_01": "c249_01_추억의_산타클로스",
	"c249_02": "c249_02_망상의_산타클로스",
	"c250_00": "c250_00_미성숙한_제니",
	"c250_01": "c250_01_수면의_제니",
	"c250_02": "c250_02_파문의_제니",
	"c251_00": "c251_00_미성숙한_가니메데",
	"c251_01": "c251_01_인도하는_가니메데",
	"c251_02": "c251_02_책략가_가니메데",
	"c252_01": "c252_01_퇴마사_아라한",
	"c252_02": "c252_02_이타_아라한",
	"c253_00": "c253_00_미성숙한_니콜",
	"c253_01": "c253_01_홀리_니콜",
	"c253_02": "c253_02_세인트_니콜",
	"c254_01": "c254_01_팝업_다비",
	"c255_01": "c255_01_팝업_모나",
	"c256_01": "c256_01_팝업_리자",
	"c257_01": "c257_01_콜로니리더_칼호스",
	"c257_02": "c257_02_콜로니리더_칼호스",
	"c258_00": "c258_00_무명의_차일드",
	"c258_01": "c258_01_상상의_픽시",
	"c258_02": "c258_02_이상의_픽시",
	"c259_00": "c259_00_미성숙한_나바루스",
	"c259_01": "c259_01_철필의_나바루스",
	"c259_02": "c259_02_필검의_나바루스",
	"c260_00": "c260_00_미성숙한_코발",
	"c260_01": "c260_01_코발",
	"c260_02": "c260_02_심미안_코발",
	"c261_01": "c261_01_백경_흑목단",
	"c261_02": "c261_02_귀인_흑목단",
	"c262_00": "c262_00_미성숙한_다프니스",
	"c262_01": "c262_01_기사_다프니스",
	"c262_02": "c262_02_용기의_다프니스",
	"c263_01": "c263_01_영웅_카드모스",
	"c263_02": "c263_02_태왕_카드모스",
	"c264_00": "c264_00_미성숙한_아를레키노",
	"c264_01": "c264_01_게으른_아를레키노",
	"c264_02": "c264_02_어릿광대_아를레키노",
	"c265_01": "c265_01_SD_모나",
	"c266_00": "c266_00_미성숙한_호루스",
	"c266_01": "c266_01_사막의_호루스",
	"c266_02": "c266_02_라_호루스",
	"c267_01": "c267_01_윤회_클레오파트라",
	"c267_02": "c267_02_파라오_클레오파트라",
	"c268_00": "c268_00_미성숙한_필리아",
	"c268_01": "c268_01_추모하는_필리아",
	"c268_02": "c268_02_수호자_필리아",
	"c269_00": "c269_00_무명의_차일드",
	"c269_01": "c269_01_카오스_픽시",
	"c269_02": "c269_02_코스모스_픽시",
	"c270_00": "c270_00_무명의_차일드",
	"c270_01": "c270_01_라이트_픽시",
	"c270_02": "c270_02_플라티나_픽시",
	"c271_00": "c271_00_무명의_차일드",
	"c271_01": "c271_01_워터_픽시",
	"c271_02": "c271_02_사파이어_픽시",
	"c272_00": "c272_00_무명의_차일드",
	"c272_01": "c272_01_리프_픽시",
	"c272_02": "c272_02_에메랄드_픽시",
	"c273_01": "c273_01_의문의_주인공",
	"c273_02": "c273_02_여학교의_주인공",
	"c274_00": "c274_00_미성숙한_바스트",
	"c274_01": "c274_01_노래하는_바스트",
	"c274_02": "c274_02_하울링_바스트",
	"c275_00": "c275_00_미성숙한_하피",
	"c275_01": "c275_01_도망자_하피",
	"c275_02": "c275_02_탈주_하피",
	"c276_00": "c276_00_미성숙한_레테",
	"c276_01": "c276_01_바텐더_레테",
	"c276_02": "c276_02_망각_레테",
	"c277_00": "c277_00_미성숙한_레우케",
	"c277_01": "c277_01_하급님프_레우케",
	"c277_02": "c277_02_파트너_레우케",
	"c278_01": "c278_01_사역마_헬라",
	"c278_02": "c278_02_프로토_헬라",
	"c279_01": "c279_01_사역마_라우페이",
	"c279_02": "c279_02_퍼스트_라우페이",
	"c280_00": "c280_00_무명의_차일드",
	"c280_01": "c280_01_유쾌한_티케",
	"c280_02": "c280_02_꿈속의_티케",
	"c280_03": "c280_03_무명의_차일드",
	"c281_01": "c281_01_도피하는_티스베",
	"c281_02": "c281_02_애수_티스베",
	"c282_01": "c282_01_탄생한_아담",
	"c282_02": "c282_02_천지창조_아담",
	"c283_01": "c283_01_메이드_모건",
	"c283_02": "c283_02_서번트_모건",
	"c284_01": "c284_01_쁘띠_모나",
	"c285_01": "c285_01_창조된_요수아",
	"c285_02": "c285_02_천지창조_요수아",
	"c286_01": "c286_01_기다리는_베르들레",
	"c286_02": "c286_02_버틀러_베르들레",
	"m001_01": "m001_01_비만의_불박쥐",
	"m001_02": "m001_02_자이안트_불박쥐",
	"m002_01": "m002_01_비만의_얼음박쥐",
	"m002_02": "m002_02_자이안트_얼음박쥐",
	"m003_01": "m003_01_분노_염룡",
	"m003_02": "m003_02_광노_염룡",
	"m004_01": "m004_01_냉혹_염룡",
	"m004_02": "m004_02_혹한_염룡",
	"m005_01": "m005_01_야무냠냠",
	"m005_02": "m005_02_아득냠냠",
	"m006_01": "m006_01_요란한_큰귀왕",
	"m006_02": "m006_02_광란_큰귀왕",
	"m007_00": "m007_00_미성숙한_테디",
	"m007_01": "m007_01_조각조각_테디",
	"m007_02": "m007_02_엉망진창_킹테디",
	"m008_01": "m008_01_딸기맛_젤라틴",
	"m008_02": "m008_02_딸기맛_푸딩",
	"m009_01": "m009_01_번개맛_젤라틴",
	"m009_02": "m009_02_번개맛_푸딩",
	"m010_01": "m010_01_블루베리_푸링",
	"m010_02": "m010_02_블루베리_포이즌",
	"m011_01": "m011_01_스트로베리_푸링",
	"m011_02": "m011_02_스트로베리_포이즌",
	"m012_01": "m012_01_동동_한해살이",
	"m012_02": "m012_02_동동_다년살이",
	"m013_01": "m013_01_당근물은_봉제인형",
	"m013_02": "m013_02_당근뱉은_봉제인형",
	"m014_01": "m014_01_조그만_먼지요정",
	"m014_02": "m014_02_캐캐묵은_먼지요정",
	"m015_01": "m015_01_태양_사막여우",
	"m015_02": "m015_02_태양_사막여우누나",
	"m016_01": "m016_01_문라이트_프로그",
	"m016_02": "m016_02_문라이트_꽃프로그",
	"m017_01": "m017_01_정의의_뿌리",
	"m017_02": "m017_02_정의의_뿌리II",
	"m018_01": "m018_01_운명의_털뭉치",
	"m018_02": "m018_02_운명의_털뭉치II",
	"m020_01": "m020_01_게으른_달팽이",
	"m020_02": "m020_02_게으른_달팽이크롬",
	"m021_01": "m021_01_게으른_노새",
	"m021_02": "m021_02_향락의_노새",
	"m022_01": "m022_01_불량스런_강아지요정",
	"m022_02": "m022_02_충성스런_강아지요정",
	"m023_01": "m023_01_초승달_도마뱀",
	"m023_02": "m023_02_블록초승달_도마뱀",
	"m025_01": "m025_01_스트롱_베리",
	"m025_02": "m025_02_버서커_베리",
	"m026_01": "m026_01_게으른_병아리",
	"m026_02": "m026_02_게으른_병아리합체",
	"m027_01": "m027_01_만드라시드",
	"m027_02": "m027_02_만드라플랜츠",
	"m028_01": "m028_01_우로_스쿼럴",
	"m028_02": "m028_02_우로_타이거",
	"m029_01": "m029_01_발광_발굽땅개",
	"m029_02": "m029_02_발화_엄니땅개",
	"m030_01": "m030_01_그린_키치볼",
	"m030_02": "m030_02_그린_키치볼",
	"m031_01": "m031_01_아낌없이_트리리",
	"m031_02": "m031_02_생명마저_트리리",
	"m032_01": "m032_01_오색_사탕거미",
	"m032_02": "m032_02_극상의_사탕거미",
	"m033_01": "m033_01_뾰족니_송사리",
	"m033_02": "m033_02_뾰족니_금붕어",
	"m034_01": "m034_01_뾰족니_치어",
	"m034_02": "m034_02_뾰족니_열대어",
	"m035_01": "m035_01_인디안_아메리카노",
	"m035_02": "m035_02_추장_아메리카노",
	"m036_00": "m036_00_무명의_차일드",
	"m036_01": "m036_01_낮은목소리의_전달자",
	"m036_02": "m036_02_무직한목소리의_전달자",
	"m037_00": "m037_00_무명의_차일드",
	"m037_01": "m037_01_그밤의_추격자",
	"m037_02": "m037_02_악몽_추격자",
	"m038_00": "m038_00_미성숙한_디아블로",
	"m038_01": "m038_01_흰날개_디아블로",
	"m038_02": "m038_02_검은날개_디아블로",
	"m039_00": "m039_00_무명의_차일드",
	"m039_01": "m039_01_파괴의_리유가",
	"m039_02": "m039_02_멸망의_리유가",
	"m040_00": "m040_00_미성숙한_체인킬러",
	"m040_01": "m040_01_보급형_체인킬러",
	"m040_02": "m040_02_한정형_체인킬러",
	"m042_01": "m042_01_지하여장군의_노리개",
	"m042_02": "m042_02_천하대장군의_노리개",
	"m044_01": "m044_01_빌헬름_기어",
	"m044_02": "m044_02_할버드_기어",
	"m045_00": "m045_00_미성숙한_정령",
	"m045_01": "m045_01_고독한_정령",
	"m045_02": "m045_02_화가난_정령",
	"m047_01": "m047_01_수수께끼의_달걀",
	"m047_02": "m047_02_콜럼부스의_달걀",
	"m048_01": "m048_01_바니_바니",
	"m048_02": "m048_02_버니_바니",
	"m049_00": "m049_00_미성숙한_박제",
	"m049_01": "m049_01_오래된_박제",
	"m049_02": "m049_02_신선한_박제",
	"m050_00": "m050_00_미성숙한_단두대",
	"m050_01": "m050_01_새벽의_단두대",
	"m050_02": "m050_02_한낮의_사형대",
	"m051_00": "m051_00_미성숙한_하데스",
	"m051_01": "m051_01_끓는_하데스",
	"m051_02": "m051_02_어둠의_하데스",
	"m052_01": "m052_01_사막_바실리",
	"m052_02": "m052_02_평원_바실리",
	"m053_00": "m053_00_미성숙한_히드라",
	"m053_01": "m053_01_혼돈의_히드라",
	"m053_02": "m053_02_탐욕의_히드라",
	"m054_00": "m054_00_미성숙한_고모라",
	"m054_01": "m054_01_심판_고모라",
	"m054_02": "m054_02_멸망_고모라",
	"m055_00": "m055_00_미성숙한_모무스",
	"m055_01": "m055_01_익살꾼_모무스",
	"m055_02": "m055_02_조소의_모무스",
	"m055_03": "m055_03_무명의_차일드",
	"m056_00": "m056_00_미성숙한_아바돈",
	"m056_01": "m056_01_악인_아바돈",
	"m056_02": "m056_02_포화_아바돈",
	"m057_00": "m057_00_미성숙한_월아",
	"m057_01": "m057_01_푸른_월아",
	"m057_02": "m057_02_검은_흑아",
	"m058_01": "m058_01_사용안함_몬스터",
	"m058_02": "m058_02_사용안함_몬스터",
	"m059_00": "m059_00_무명의_차일드",
	"m059_01": "m059_01_안전모_바주카",
	"m059_02": "m059_02_강철모_바주카",
	"m060_01": "m060_01_드림이터",
	"m060_02": "m060_02_나이트메어_이터",
	"m061_01": "m061_01_딸기맛_주사기",
	"m061_02": "m061_02_큰딸기맛_주사기",
	"m062_01": "m062_01_포도맛_주사기",
	"m062_02": "m062_02_포도맛_주사기",
	"m063_00": "m063_00_무명의_차일드",
	"m063_01": "m063_01_포이즌_앰플",
	"m063_02": "m063_02_뉴포이즌_앰플",
	"m064_01": "m064_01_아기돼지_푸꾸리",
	"m064_02": "m064_02_아기돼지_푸꾸리진",
	"m065_01": "m065_01_아기돼지_꼬꾸리",
	"m065_02": "m065_02_아기돼지_꼬꾸리진",
	"m066_01": "m066_01_아기돼지_꾸꾸리",
	"m066_02": "m066_02_아기돼지_꾸꾸리진",
	"m067_01": "m067_01_아쿠_푸드",
	"m067_02": "m067_02_빅아쿠_푸드",
	"m068_01": "m068_01_다쿠_푸드",
	"m068_02": "m068_02_빅다쿠_푸드",
	"m069_01": "m069_01_라이_푸드",
	"m069_02": "m069_02_빅라이_푸드",
	"m070_01": "m070_01_묶인_쇠사슬",
	"m070_02": "m070_02_해방_쇠사슬",
	"m071_01": "m071_01_묶인_쇠사슬",
	"m071_02": "m071_02_해방_쇠사슬",
	"m072_01": "m072_01_묶인_쇠사슬",
	"m072_02": "m072_02_해방_쇠사슬",
	"m073_01": "m073_01_큐어_큐브",
	"m073_02": "m073_02_큐어_큐브",
	"m074_01": "m074_01_포이_큐브",
	"m074_02": "m074_02_포이_큐브",
	"m075_01": "m075_01_아쿠_큐브",
	"m075_02": "m075_02_아쿠_큐브",
	"m076_01": "m076_01_하니_큐브",
	"m076_02": "m076_02_하니_큐브",
	"m077_00": "m077_00_미성숙한_모아",
	"m077_01": "m077_01_큐브_모아",
	"m077_02": "m077_02_큰큐브_모아",
	"m078_01": "m078_01_페어리_고치",
	"m078_02": "m078_02_페어리_브로치",
	"m079_01": "m079_01_스톤_고치",
	"m079_02": "m079_02_스톤_브로치",
	"m080_01": "m080_01_홍옥_고치",
	"m080_02": "m080_02_홍옥_브로치",
	"m081_01": "m081_01_샤인_고치",
	"m081_02": "m081_02_샤인_브로치",
	"m082_01": "m082_01_콜드_고치",
	"m082_02": "m082_02_콜드_브로치",
	"m083_01": "m083_01_밤_고치",
	"m083_02": "m083_02_밤_브로치",
	"m084_01": "m084_01_파이_큐브",
	"m084_02": "m084_02_파이_큐브",
	"m085_01": "m085_01_그레이_큐브",
	"m085_02": "m085_02_그레이_큐브",
	"m086_01": "m086_01_묶인_쇠사슬",
	"m086_02": "m086_02_해방_쇠사슬",
	"m087_01": "m087_01_묶인_쇠사슬",
	"m087_02": "m087_02_해방_쇠사슬",
	"m088_01": "m088_01_묶인_쇠사슬",
	"m088_02": "m088_02_해방_쇠사슬",
	"m089_01": "m089_01_아기돼지_무꾸리",
	"m089_02": "m089_02_아기돼지_무꾸리진",
	"m090_01": "m090_01_아기돼지_흐꾸리",
	"m090_02": "m090_02_아기돼지_흐꾸리진",
	"m091_01": "m091_01_아기돼지",
	"m091_02": "m091_02_아기돼지_진",
	"m092_01": "m092_01_수액_주사기",
	"m092_02": "m092_02_수액_주사기",
	"m093_01": "m093_01_빛의_주사기",
	"m093_02": "m093_02_빛의_주사기",
	"m094_01": "m094_01_무명_주사기",
	"m094_02": "m094_02_무명_주사기",
	"m095_01": "m095_01_물의_주사기",
	"m095_02": "m095_02_물의_주사기",
	"m096_01": "m096_01_라이트_키치볼",
	"m096_02": "m096_02_엔젤라이트_키치볼",
	"m097_01": "m097_01_블루_키치볼",
	"m097_02": "m097_02_엔젤블루_키치볼",
	"m098_01": "m098_01_퍼플_키치볼",
	"m098_02": "m098_02_엔젤퍼플_키치볼",
	"m099_01": "m099_01_키치볼",
	"m099_02": "m099_02_엔젤_키치볼",
	"m100_01": "m100_01_레드_키치볼",
	"m100_02": "m100_02_엔젤_키치볼",
	"m101_01": "m101_01_작은_발그람",
	"m101_02": "m101_02_큰_발그람",
	"m102_01": "m102_01_작은_파르람",
	"m102_02": "m102_02_큰_파르람",
	"m103_01": "m103_01_작은_노르람",
	"m103_02": "m103_02_큰_노르람",
	"m104_01": "m104_01_작은_자르람",
	"m104_02": "m104_02_큰_자르람",
	"m105_01": "m105_01_작은_차르람",
	"m105_02": "m105_02_큰_차르람",
	"m106_01": "m106_01_작은_흐르람",
	"m106_02": "m106_02_큰_흐르람",
	"m107_01": "m107_01_그린_푸드",
	"m107_02": "m107_02_빅그린_푸드",
	"m108_01": "m108_01_그레이_푸드",
	"m108_02": "m108_02_빅그레이_푸드",
	"m109_01": "m109_01_파이어_푸드",
	"m109_02": "m109_02_큰파이어_푸드",
	"m110_01": "m110_01_초롱",
	"m110_02": "m110_02_초롱초롱",
	"m111_01": "m111_01_화롱",
	"m111_02": "m111_02_화롱화롱",
	"m112_01": "m112_01_차롱",
	"m112_02": "m112_02_차롱차롱",
	"m113_01": "m113_01_다롱",
	"m113_02": "m113_02_다롱_다롱",
	"m114_01": "m114_01_바롱",
	"m114_02": "m114_02_바롱바롱",
	"m115_01": "m115_01_아롱",
	"m115_02": "m115_02_아롱아롱",
	"m116_01": "m116_01_디펜서_바우",
	"m116_02": "m116_02_챔피언_바우",
	"m117_01": "m117_01_그로우캣_더미",
	"m117_02": "m117_02_그로우캣_데빌",
	"m118_01": "m118_01_카타나_슬래셔",
	"m118_02": "m118_02_막무가내_슬레셔",
	"m119_01": "m119_01_카타나_닌자",
	"m119_02": "m119_02_막무가내_닌자",
	"m120_01": "m120_01_카타나_어쌔신",
	"m120_02": "m120_02_막무가내_어쌔신",
	"m121_01": "m121_01_카타나_무사",
	"m121_02": "m121_02_막무가내_무사",
	"m122_01": "m122_01_카타나_무명인",
	"m122_02": "m122_02_막무가내_무명인",
	"m123_01": "m123_01_카타나_그림자",
	"m123_02": "m123_02_막무가내_그림자",
	"m124_01": "m124_01_타는_주시자",
	"m124_02": "m124_02_황혼_주시자",
	"m125_01": "m125_01_얼어붙은_주시자",
	"m125_02": "m125_02_새벽_주시자",
	"m126_01": "m126_01_검은_주시자",
	"m126_02": "m126_02_흑암_주시자",
	"m127_01": "m127_01_숲의_주시자",
	"m127_02": "m127_02_녹암_주시자",
	"m128_01": "m128_01_빛의_주시자",
	"m128_02": "m128_02_태양_주시자",
	"m129_01": "m129_01_텅빈_주시자",
	"m129_02": "m129_02_혼돈_주시자",
	"m130_01": "m130_01_플레임_팝업",
	"m130_02": "m130_02_샐러맨더_팝업",
	"m131_01": "m131_01_워터_팝업",
	"m131_02": "m131_02_운디네_팝업",
	"m132_01": "m132_01_플랜트_팝업",
	"m132_02": "m132_02_드라이어드_팝업",
	"m133_01": "m133_01_라이트_팝업",
	"m133_02": "m133_02_피닉스_팝업",
	"m134_01": "m134_01_다크_팝업",
	"m134_02": "m134_02_할로윈_팝업",
	"m135_01": "m135_01_그레이_팝업",
	"m135_02": "m135_02_카오스_팝업",
	"m136_00": "m136_00_미성숙한_레이디",
	"m136_01": "m136_01_구속구_레이디",
	"m136_02": "m136_02_매드_레이디",
	"m137_01": "m137_01_보타이_벨보이",
	"m137_02": "m137_02_매드_벨보이",
	"m138_01": "m138_01_푸르른_흐르람",
	"m139_01": "m139_01_화려한_흐르람",
	"m140_01": "m140_01_황금_흐르람",
	"m141_00": "m141_00_미성숙한_할로윈",
	"m141_01": "m141_01_드림_할로윈",
	"m141_02": "m141_02_나이트메어_할로윈",
	"m142_01": "m142_01_리벤저걸_레드",
	"m142_02": "m142_02_리벤저걸_플레임",
	"m143_01": "m143_01_리벤저걸_블루",
	"m143_02": "m143_02_리벤저걸_플루드",
	"m144_01": "m144_01_리벤저걸_그린",
	"m144_02": "m144_02_리벤저걸_블룸",
	"m145_01": "m145_01_리벤저걸_라이트",
	"m145_02": "m145_02_리벤저걸_플래시",
	"m146_01": "m146_01_리벤저걸_퍼플",
	"m146_02": "m146_02_리벤저걸_다크니스",
	"m147_01": "m147_01_리벤저걸_그레이",
	"m147_02": "m147_02_리벤저걸_카오스",
	"m148_01": "m148_01_노이즈_원",
	"m148_02": "m148_02_노이즈_피크",
	"m149_01": "m149_01_디제잉_헤르츠",
	"m149_02": "m149_02_레볼루션_헤르츠",
	"m150_00": "m150_00_무명의_차일드",
	"m150_01": "m150_01_페이크_해트트릭",
	"m150_02": "m150_02_체크메이트_해트트릭",
	"m151_01": "m151_01_매드바니_암즈",
	"m151_02": "m151_02_매드바니_스피릿",
	"m152_01": "m152_01_스니커_파이터",
	"m152_02": "m152_02_스니커_챔피언",
	"m153_01": "m153_01_흉몽_멘티",
	"m153_02": "m153_02_몽마_멘티",
	"m154_00": "m154_00_미성숙한_궁닐",
	"m154_01": "m154_01_다크_궁닐",
	"m154_02": "m154_02_오더메이드_궁닐",
	"m155_01": "m155_01_작은_뽀로롱",
	"m155_02": "m155_02_무명의_차일드",
	"m156_01": "m156_01_작은_노로롱",
	"m156_02": "m156_02_무명의_차일드",
	"m157_01": "m157_01_작은_초로롱",
	"m157_02": "m157_02_무명의_차일드",
	"m158_01": "m158_01_작은_푸로롱",
	"m158_02": "m158_02_무명의_차일드",
	"m159_01": "m159_01_작은_자로롱",
	"m159_02": "m159_02_무명의_차일드",
	"m160_01": "m160_01_작은_오로롱",
	"m160_02": "m160_02_무명의_차일드",
	"m161_01": "m161_01_작은_발그라미",
	"m161_02": "m161_02_무명의_차일드",
	"m162_01": "m162_01_작은_노르라미",
	"m162_02": "m162_02_무명의_차일드",
	"m163_01": "m163_01_작은_차르라미",
	"m163_02": "m163_02_무명의_차일드",
	"m164_01": "m164_01_작은_푸르라미",
	"m164_02": "m164_02_무명의_차일드",
	"m165_01": "m165_01_작은_자르라미",
	"m165_02": "m165_02_무명의_차일드",
	"m166_01": "m166_01_작은_오로라미",
	"m166_02": "m166_02_무명의_차일드",
	"m167_01": "m167_01_작은_발그라밈",
	"m167_02": "m167_02_무명의_차일드",
	"m168_01": "m168_01_작은_노르라밈",
	"m168_02": "m168_02_무명의_차일드",
	"m169_01": "m169_01_작은_차르라밈",
	"m169_02": "m169_02_무명의_차일드",
	"m170_01": "m170_01_작은_푸르라밈",
	"m170_02": "m170_02_무명의_차일드",
	"m171_01": "m171_01_작은_자르라밈",
	"m171_02": "m171_02_무명의_차일드",
	"m172_01": "m172_01_작은_오로라밈",
	"m172_02": "m172_02_무명의_차일드",
	"m173_01": "m173_01_큰_발그라밈",
	"m173_02": "m173_02_무명의_차일드",
	"m174_01": "m174_01_큰_노르라밈",
	"m174_02": "m174_02_무명의_차일드",
	"m175_01": "m175_01_큰_차르라밈",
	"m175_02": "m175_02_무명의_차일드",
	"m176_01": "m176_01_큰_파르라밈",
	"m176_02": "m176_02_무명의_차일드",
	"m177_01": "m177_01_큰_자르라밈",
	"m177_02": "m177_02_무명의_차일드",
	"m178_01": "m178_01_큰_오로라밈",
	"m178_02": "m178_02_무명의_차일드",
	"m179_01": "m179_01_카이저_발그람",
	"m179_02": "m179_02_무명의_차일드",
	"m180_01": "m180_01_카이저_노르람",
	"m180_02": "m180_02_무명의_차일드",
	"m181_01": "m181_01_카이저_차르람",
	"m181_02": "m181_02_무명의_차일드",
	"m182_01": "m182_01_카이저_푸르람",
	"m182_02": "m182_02_무명의_차일드",
	"m183_01": "m183_01_카이저_자르람",
	"m183_02": "m183_02_무명의_차일드",
	"m184_01": "m184_01_카이저_오로람",
	"m184_02": "m184_02_무명의_차일드",
	"m185_01": "m185_01_조용한_액티언",
	"m185_02": "m185_02_은둔하는_액티언",
	"m186_01": "m186_01_순수한_사브",
	"m186_02": "m186_02_암전_사브",
	"m187_01": "m187_01_표류하는_다곤",
	"m187_02": "m187_02_방랑하는_다곤",
	"m188_01": "m188_01_고대의_골드코인",
	"m188_02": "m188_02_욕구의_골드코인",
	"m189_01": "m189_01_깜짝_보물상자",
	"m189_02": "m189_02_끔찍_보물상자",
	"m190_01": "m190_01_열혈의_박서",
	"m190_02": "m190_02_염화의_박서",
	"m191_00": "m191_00_미성숙한_키메이라",
	"m191_01": "m191_01_침묵_키메이라",
	"m191_02": "m191_02_계시_키메이라",
	"m192_01": "m192_01_적왕_혈룡",
	"m192_02": "m192_02_적황_혈룡",
	"m193_01": "m193_01_와글와글_털뭉치",
	"m193_02": "m193_02_와글와글_털뭉치II",
	"m194_01": "m194_01_오목눈_초론",
	"m194_02": "m194_02_초론_초론",
	"m195_01": "m195_01_오목눈_바론",
	"m195_02": "m195_02_바론_바론",
	"m196_01": "m196_01_오목눈_화론",
	"m196_02": "m196_02_화론_화론",
	"m197_01": "m197_01_오목눈_차론",
	"m197_02": "m197_02_차론_차론",
	"m198_01": "m198_01_오목눈_다론",
	"m198_02": "m198_02_다론_다론",
	"m199_01": "m199_01_청염_수룡",
	"m199_02": "m199_02_청황_수룡",
	"m200_00": "m200_00_미성숙한_앙크",
	"m200_01": "m200_01_수호관_앙크",
	"m200_02": "m200_02_집행관_앙크",
	"m201_00": "m201_00_미성숙한_바주카맨",
	"m201_01": "m201_01_무장_바주카맨",
	"m201_02": "m201_02_완전무장_바주카맨",
	"m202_00": "m202_00_미성숙한_바주람보",
	"m202_01": "m202_01_폭격_바주람보",
	"m202_02": "m202_02_스턴드_바주람보",
	"m203_00": "m203_00_미성숙한_브레멘",
	"m203_01": "m203_01_빙글빙글_브레맨",
	"m203_02": "m203_02_팽글팽글_브레맨",
	"m204_01": "m204_01_무명의_차일드",
	"m204_02": "m204_02_무명의_차일드",
	"m205_01": "m205_01_쫓기는_발프",
	"m205_02": "m205_02_위치_발프",
	"m206_01": "m206_01_무정한_부꾸두들",
	"m206_02": "m206_02_참살자_부꾸두들",
	"m207_01": "m207_01_무명의_차일드",
	"m207_02": "m207_02_무명의_차일드",
	"m208_01": "m208_01_무명의_차일드",
	"m208_02": "m208_02_무명의_차일드",
	"m209_01": "m209_01_무명의_차일드",
	"m209_02": "m209_02_무명의_차일드",
	"m211_01": "m211_01_무명의_차일드",
	"m211_02": "m211_02_무명의_차일드"
}